NumpyHePandasShujufenxiShiyongZhinanChuyiFix1/README.md
NumpyHePandasShujufenxiShiyongZhinanChuyiFix1/__init__.py
NumpyHePandasShujufenxiShiyongZhinanChuyiFix1/__main__.py
NumpyHePandasShujufenxiShiyongZhinanChuyiFix1/file.epub
NumpyHePandasShujufenxiShiyongZhinanChuyiFix1/index.html
NumpyHePandasShujufenxiShiyongZhinanChuyiFix1/css/__init__.py
NumpyHePandasShujufenxiShiyongZhinanChuyiFix1/css/annotations.css
NumpyHePandasShujufenxiShiyongZhinanChuyiFix1/css/main.css
NumpyHePandasShujufenxiShiyongZhinanChuyiFix1/css/normalize.css
NumpyHePandasShujufenxiShiyongZhinanChuyiFix1/css/popup.css
NumpyHePandasShujufenxiShiyongZhinanChuyiFix1/font/__init__.py
NumpyHePandasShujufenxiShiyongZhinanChuyiFix1/font/fontello.eot
NumpyHePandasShujufenxiShiyongZhinanChuyiFix1/font/fontello.svg
NumpyHePandasShujufenxiShiyongZhinanChuyiFix1/font/fontello.ttf
NumpyHePandasShujufenxiShiyongZhinanChuyiFix1/font/fontello.woff
NumpyHePandasShujufenxiShiyongZhinanChuyiFix1/img/__init__.py
NumpyHePandasShujufenxiShiyongZhinanChuyiFix1/img/annotator-glyph-sprite.png
NumpyHePandasShujufenxiShiyongZhinanChuyiFix1/img/annotator-icon-sprite.png
NumpyHePandasShujufenxiShiyongZhinanChuyiFix1/img/apple-touch-icon.png
NumpyHePandasShujufenxiShiyongZhinanChuyiFix1/img/cancelfullscreen.png
NumpyHePandasShujufenxiShiyongZhinanChuyiFix1/img/close.png
NumpyHePandasShujufenxiShiyongZhinanChuyiFix1/img/fullscreen.png
NumpyHePandasShujufenxiShiyongZhinanChuyiFix1/img/loader.gif
NumpyHePandasShujufenxiShiyongZhinanChuyiFix1/img/menu-icon.png
NumpyHePandasShujufenxiShiyongZhinanChuyiFix1/img/save.png
NumpyHePandasShujufenxiShiyongZhinanChuyiFix1/img/saved.png
NumpyHePandasShujufenxiShiyongZhinanChuyiFix1/img/settings-s.png
NumpyHePandasShujufenxiShiyongZhinanChuyiFix1/img/settings.png
NumpyHePandasShujufenxiShiyongZhinanChuyiFix1/img/star.png
NumpyHePandasShujufenxiShiyongZhinanChuyiFix1/js/__init__.py
NumpyHePandasShujufenxiShiyongZhinanChuyiFix1/js/epub.js
numpy_he_pandas_shujufenxi_shiyong_zhinan_chuyi_fix1-2025.3.24.1.dist-info/METADATA
numpy_he_pandas_shujufenxi_shiyong_zhinan_chuyi_fix1-2025.3.24.1.dist-info/WHEEL
numpy_he_pandas_shujufenxi_shiyong_zhinan_chuyi_fix1-2025.3.24.1.dist-info/entry_points.txt
numpy_he_pandas_shujufenxi_shiyong_zhinan_chuyi_fix1-2025.3.24.1.dist-info/top_level.txt
numpy_he_pandas_shujufenxi_shiyong_zhinan_chuyi_fix1-2025.3.24.1.dist-info/RECORD
